{"pagelen": 50, "values": [{"update": {"description": "* Reorganize systems into plugins that can be loaded at runtime.\r\n\r\n    * Adds a SystemPluginManager for finding and loading plugins.\r\n    * Adds a NullSystem plugin to verify multiple plugins can be loaded.\r\n    \r\n* Continued work on systems, focused on loading mechanism.\r\n\r\n    * SystemPluginManger -> SystemManager\r\n    * Make System an interface.\r\n    * Add configuration parsing similar to ign-gui\r\n    * Add a test system and configuration\r\n    \r\n* Load systems by name, in the case that multiple are in the same library.\r\n* Codecheck.\r\n* Rework of system\\_plugins with new structure taken into account.", "title": "System plugins", "destination": {"commit": {"hash": "ca10816b3589", "type": "commit", "links": {"self": {"href": "data/repositories/ignitionrobotics/ign-gazebo/commit/ca10816b3589.json"}, "html": {"href": "#!/ignitionrobotics/ign-gazebo/commits/ca10816b3589"}}}, "repository": {"links": {"self": {"href": "data/repositories/ignitionrobotics/ign-gazebo.json"}, "html": {"href": "#!/ignitionrobotics/ign-gazebo"}, "avatar": {"href": "data/bytebucket.org/ravatar/{f98d11fe-f287-4dfb-99c3-e2b76a13232e}ts=2082645"}}, "type": "repository", "name": "ign-gazebo", "full_name": "ignitionrobotics/ign-gazebo", "uuid": "{f98d11fe-f287-4dfb-99c3-e2b76a13232e}"}, "branch": {"name": "default"}}, "reason": "", "source": {"commit": {"hash": "dfa3ffd94503", "type": "commit", "links": {"self": {"href": "data/repositories/ignitionrobotics/ign-gazebo/commit/dfa3ffd94503.json"}, "html": {"href": "#!/ignitionrobotics/ign-gazebo/commits/dfa3ffd94503"}}}, "repository": {"links": {"self": {"href": "data/repositories/ignitionrobotics/ign-gazebo.json"}, "html": {"href": "#!/ignitionrobotics/ign-gazebo"}, "avatar": {"href": "data/bytebucket.org/ravatar/{f98d11fe-f287-4dfb-99c3-e2b76a13232e}ts=2082645"}}, "type": "repository", "name": "ign-gazebo", "full_name": "ignitionrobotics/ign-gazebo", "uuid": "{f98d11fe-f287-4dfb-99c3-e2b76a13232e}"}, "branch": {"name": "system_plugins"}}, "state": "OPEN", "author": {"display_name": "Michael Carroll", "uuid": "{17dbbc15-cbc0-42f0-a985-cde9061c78a0}", "links": {"self": {"href": "https://api.bitbucket.org/2.0/users/%7B17dbbc15-cbc0-42f0-a985-cde9061c78a0%7D"}, "html": {"href": "https://bitbucket.org/%7B17dbbc15-cbc0-42f0-a985-cde9061c78a0%7D/"}, "avatar": {"href": "https://avatar-management--avatars.us-west-2.prod.public.atl-paas.net/557058:65740f22-cc56-4418-9608-7e17d0ed47b7/2aa259f5-4de1-4f68-9156-eded72041d84/128"}}, "nickname": "Michael Carroll", "type": "user", "account_id": "557058:65740f22-cc56-4418-9608-7e17d0ed47b7"}, "date": "2018-08-22T18:42:27.167859+00:00"}, "pull_request": {"type": "pullrequest", "id": 26, "links": {"self": {"href": "data/repositories/ignitionrobotics/ign-gazebo/pullrequests/26.json"}, "html": {"href": "#!/ignitionrobotics/ign-gazebo/pull-requests/26"}}, "title": "System plugins"}}]}